{"MD Fields":[{"exclution":"VERSION","objName":"MD Fields","condition":"OWNER_FLG='CM' AND OWNER_FLG='CM'","upSw":"T","frSw":"T","inSw":"T","table":"CI_MD_FLD","dlSw":"F"},{"exclution":"VERSION","objName":"MD Fields","condition":"FLD_NAME IN (SELECT FLD_NAME FROM CI_MD_FLD WHERE OWNER_FLG = 'CM') AND OWNER_FLG='CM'","upSw":"T","frSw":"T","inSw":"T","table":"CI_MD_FLD_L","dlSw":"F"}],"XAI Receiver":[{"exclution":"VERSION","objName":"XAI Receiver","condition":"","upSw":"T","frSw":"T","inSw":"T","table":"CI_XAI_RCVR","dlSw":"F"},{"exclution":"VERSION","objName":"XAI Receiver","condition":"","upSw":"T","frSw":"T","inSw":"T","table":"CI_XAI_RCVR_L","dlSw":"F"},{"exclution":"VERSION","objName":"XAI Receiver","condition":"","upSw":"T","frSw":"T","inSw":"T","table":"CI_XAI_RCVR_RSP","dlSw":"F"}],"XAI JNDI SVR*":[{"exclution":"VERSION","objName":"XAI JNDI SVR*","condition":"","upSw":"T","frSw":"T","inSw":"T","table":"CI_XAI_JNDI_SVR","dlSw":"F"},{"exclution":"VERSION","objName":"XAI JNDI SVR*","condition":"","upSw":"T","frSw":"T","inSw":"T","table":"CI_XAI_JNDI_SVR_L","dlSw":"F"}],"FK Reference":[{"exclution":"VERSION","objName":"FK Reference","condition":"FK_REF_CD like 'CM%' AND OWNER_FLG='CM'","upSw":"T","frSw":"T","inSw":"T","table":"CI_FK_REF","dlSw":"F"},{"exclution":"VERSION","objName":"FK Reference","condition":"FK_REF_CD like 'CM%' AND OWNER_FLG='CM'","upSw":"T","frSw":"T","inSw":"T","table":"CI_FK_REF_L","dlSw":"F"}],"Portal":[{"exclution":"VERSION","objName":"Portal","condition":"PORTAL_CD LIKE 'CM%' AND OWNER_FLG='CM'","upSw":"T","frSw":"T","inSw":"T","table":"CI_PORTAL","dlSw":"F"},{"exclution":"VERSION","objName":"Portal","condition":"PORTAL_CD LIKE 'CM%' AND OWNER_FLG='CM'","upSw":"T","frSw":"T","inSw":"T","table":"CI_PORTAL_L","dlSw":"F"}],"Scripts":[{"exclution":"VERSION","objName":"Scripts","condition":"UPPER(SCR_CD) LIKE 'CM%' AND OWNER_FLG='CM'","upSw":"T","frSw":"T","inSw":"T","table":"CI_SCR","dlSw":"F"},{"exclution":"VERSION","objName":"Scripts","condition":"UPPER(SCR_CD) LIKE 'CM%' AND OWNER_FLG='CM'","upSw":"T","frSw":"T","inSw":"T","table":"CI_SCR_CRT","dlSw":"F"},{"exclution":"VERSION","objName":"Scripts","condition":"UPPER(SCR_CD) LIKE 'CM%' AND OWNER_FLG='CM'","upSw":"T","frSw":"T","inSw":"T","table":"CI_SCR_CRT_GRP","dlSw":"F"},{"exclution":"VERSION","objName":"Scripts","condition":"UPPER(SCR_CD) LIKE 'CM%' AND OWNER_FLG='CM'","upSw":"T","frSw":"T","inSw":"T","table":"CI_SCR_CRT_GRP_L","dlSw":"F"},{"exclution":"VERSION","objName":"Scripts","condition":"UPPER(SCR_CD) LIKE 'CM%' AND UPPER(DA_NAME) LIKE 'CM%' AND OWNER_FLG='CM'","upSw":"T","frSw":"T","inSw":"T","table":"CI_SCR_DA","dlSw":"F"},{"exclution":"VERSION","objName":"Scripts","condition":"UPPER(SCR_CD) LIKE 'CM%' AND UPPER(FUNC_CD) LIKE 'CM%' AND UPPER(FUNC_FLD_NAME) LIKE 'CM%' AND OWNER_FLG='CM'","upSw":"T","frSw":"T","inSw":"T","table":"CI_SCR_FLD_MAP","dlSw":"F"},{"exclution":"VERSION","objName":"Scripts","condition":"UPPER(SCR_CD) LIKE 'CM%' AND OWNER_FLG='CM'","upSw":"T","frSw":"T","inSw":"T","table":"CI_SCR_L","dlSw":"F"},{"exclution":"VERSION","objName":"Scripts","condition":"UPPER(SCR_CD) LIKE 'CM%' AND OWNER_FLG='CM'","upSw":"T","frSw":"T","inSw":"T","table":"CI_SCR_PRMPT","dlSw":"F"},{"exclution":"VERSION","objName":"Scripts","condition":"UPPER(SCR_CD) LIKE 'CM%' AND OWNER_FLG='CM'","upSw":"T","frSw":"T","inSw":"T","table":"CI_SCR_PRMPT_L","dlSw":"F"},{"exclution":"VERSION","objName":"Scripts","condition":"UPPER(SCR_CD) LIKE 'CM%' AND OWNER_FLG='CM'","upSw":"T","frSw":"T","inSw":"T","table":"CI_SCR_STEP","dlSw":"F"},{"exclution":"VERSION","objName":"Scripts","condition":"UPPER(SCR_CD) LIKE 'CM%' AND OWNER_FLG='CM'","upSw":"T","frSw":"T","inSw":"T","table":"CI_SCR_STEP_L","dlSw":"F"}],"Maintenance Object Options":[{"exclution":"VERSION","objName":"Maintenance Object Options","condition":"OWNER_FLG='CM'","upSw":"T","frSw":"T","inSw":"T","table":"CI_MD_MO_OPT","dlSw":"F"}],"Constants":[{"exclution":"VERSION","objName":"Constants","condition":"CONST_ID like 'CM%' AND OWNER_FLG='CM'","upSw":"T","frSw":"T","inSw":"T","table":"CI_MD_CONST","dlSw":"F"},{"exclution":"VERSION","objName":"Constants","condition":"CONST_ID like 'CM%' AND OWNER_FLG='CM'","upSw":"T","frSw":"T","inSw":"T","table":"CI_MD_CONST_FLD","dlSw":"F"}],"XAI Sender":[{"exclution":"VERSION","objName":"XAI Sender","condition":"","upSw":"T","frSw":"T","inSw":"T","table":"CI_XAI_SENDER","dlSw":"F"},{"exclution":"VERSION","objName":"XAI Sender","condition":"","upSw":"T","frSw":"T","inSw":"T","table":"CI_XAI_SENDER_L","dlSw":"F"}],"Portal Zone":[{"exclution":"VERSION","objName":"Portal Zone","condition":"((PORTAL_CD LIKE 'CM%') OR (ZONE_CD LIKE 'CM%')) AND OWNER_FLG='CM'","upSw":"T","frSw":"T","inSw":"T","table":"CI_PORTAL_ZONE","dlSw":"F"}],"Tool Rep":[{"exclution":"VERSION","objName":"Tool Rep","condition":"OBJECT_NAME LIKE 'CM%'","upSw":"T","frSw":"T","inSw":"T","table":"CI_MD_TOOLREP_XML","dlSw":"F"},{"exclution":"VERSION","objName":"Tool Rep","condition":"OBJECT_NAME LIKE 'CM%'","upSw":"T","frSw":"T","inSw":"T","table":"CI_MD_TOOL_REP","dlSw":"F"}],"To Do Type":[{"exclution":"VERSION","objName":"To Do Type","condition":"TD_TYPE_CD like 'CM%' AND OWNER_FLG='CM'","upSw":"T","frSw":"T","inSw":"T","table":"CI_TD_TYPE","dlSw":"F"},{"exclution":"VERSION","objName":"To Do Type","condition":"TD_TYPE_CD like 'CM%' AND OWNER_FLG='CM'","upSw":"T","frSw":"T","inSw":"T","table":"CI_TD_TYPE_L","dlSw":"F"},{"exclution":"VERSION","objName":"To Do Type","condition":"TD_TYPE_CD like 'CM%' AND OWNER_FLG='CM'","upSw":"T","frSw":"T","inSw":"T","table":"CI_TD_SRTKEY_TY","dlSw":"F"},{"exclution":"VERSION","objName":"To Do Type","condition":"TD_TYPE_CD like 'CM%' AND OWNER_FLG='CM'","upSw":"T","frSw":"T","inSw":"T","table":"CI_TD_DRLKEY_TY","dlSw":"F"},{"exclution":"VERSION","objName":"To Do Type","condition":"TD_TYPE_CD like 'CM%' AND OWNER_FLG='CM'","upSw":"T","frSw":"T","inSw":"T","table":"CI_TD_SRTKEY_TY_L","dlSw":"F"}],"XAI Service Parameters":[{"exclution":"VERSION","objName":"XAI Service Parameters","condition":"XAI_IN_SVC_ID like 'CM%' AND OWNER_FLG='CM'","upSw":"T","frSw":"T","inSw":"T","table":"CI_XAI_SVC_PARM","dlSw":"F"},{"exclution":"VERSION","objName":"XAI Service Parameters","condition":"XAI_IN_SVC_ID like 'CM%' AND OWNER_FLG='CM'","upSw":"T","frSw":"T","inSw":"T","table":"CI_XAI_SVC_VERS","dlSw":"F"},{"exclution":"VERSION","objName":"XAI Service Parameters","condition":"XAI_IN_SVC_ID like 'CM%' AND OWNER_FLG='CM'","upSw":"T","frSw":"T","inSw":"T","table":"CI_XAI_SVC_VERS_L","dlSw":"F"}],"XAI Proc*":[{"exclution":"VERSION","objName":"XAI Proc*","condition":"DB_PROC_CD like 'CM%'","upSw":"T","frSw":"T","inSw":"T","table":"CI_DB_PROC","dlSw":"F"},{"exclution":"VERSION","objName":"XAI Proc*","condition":"DB_PROC_CD like 'CM%'","upSw":"T","frSw":"T","inSw":"T","table":"CI_DB_PROC_L","dlSw":"F"}],"Navigation Option":[{"exclution":"VERSION","objName":"Navigation Option","condition":"UPPER(NAV_OPT_CD) like 'CM%' AND OWNER_FLG='CM'","upSw":"T","frSw":"T","inSw":"T","table":"CI_NAV_OPT","dlSw":"F"},{"exclution":"VERSION","objName":"Navigation Option","condition":"UPPER(NAV_OPT_CD) like 'CM%' AND OWNER_FLG='CM'","upSw":"T","frSw":"T","inSw":"T","table":"CI_NAV_OPT_CTXT","dlSw":"F"},{"exclution":"VERSION","objName":"Navigation Option","condition":"UPPER(NAV_OPT_CD) like 'CM%' AND OWNER_FLG='CM'","upSw":"T","frSw":"T","inSw":"T","table":"CI_NAV_OPT_L","dlSw":"F"},{"exclution":"VERSION","objName":"Navigation Option","condition":"UPPER(NAV_OPT_CD) like 'CM%' AND OWNER_FLG='CM'","upSw":"T","frSw":"T","inSw":"T","table":"CI_NAV_OPT_USG","dlSw":"F"}],"Zone":[{"exclution":"VERSION","objName":"Zone","condition":"ZONE_CD LIKE 'CM%' AND OWNER_FLG='CM'","upSw":"T","frSw":"T","inSw":"T","table":"CI_ZONE","dlSw":"F"},{"exclution":"VERSION","objName":"Zone","condition":"ZONE_CD LIKE 'CM%' AND OWNER_FLG='CM'","upSw":"T","frSw":"T","inSw":"T","table":"CI_ZONE_L","dlSw":"F"},{"exclution":"VERSION","objName":"Zone","condition":"((ZONE_CD LIKE 'CM%') OR (ZONE_HDL_CD LIKE 'CM%')) AND OWNER_FLG='CM'","upSw":"T","frSw":"T","inSw":"T","table":"CI_ZONE_PRM","dlSw":"F"},{"exclution":"","objName":"Zone","condition":"ZONE_HDL_CD LIKE 'CM%' AND OWNER_FLG='CM'","upSw":"T","frSw":"T","inSw":"T","table":"CI_ZONE_HDL","dlSw":"F"},{"exclution":"VERSION","objName":"Zone","condition":"ZONE_HDL_CD LIKE 'CM%' AND OWNER_FLG='CM'","upSw":"T","frSw":"T","inSw":"T","table":"CI_ZONE_HDL_L","dlSw":"F"},{"exclution":"VERSION","objName":"Zone","condition":"ZONE_HDL_CD LIKE 'CM%' AND OWNER_FLG='CM'","upSw":"T","frSw":"T","inSw":"T","table":"CI_ZONE_HDL_PRM","dlSw":"F"},{"exclution":"VERSION","objName":"Zone","condition":"ZONE_HDL_CD LIKE 'CM%' AND OWNER_FLG='CM'","upSw":"T","frSw":"T","inSw":"T","table":"CI_ZONE_HDL_PRM_L","dlSw":"F"},{"exclution":"VERSION","objName":"Zone","condition":"SEQ_NAME LIKE 'CM%' AND OWNER_FLG='CM'","upSw":"T","frSw":"T","inSw":"T","table":"CI_SEQ","dlSw":"F"},{"exclution":"SORT_SEQ,VERSION","objName":"Zone","condition":"UPPER(NAVIGATION_KEY) LIKE 'CM%' AND UPPER(ZONE_CD) LIKE 'CM%' AND OWNER_FLG='CM'","upSw":"T","frSw":"T","inSw":"T","table":"CI_UI_ZONE","dlSw":"F"}],"Program":[{"exclution":"VERSION","objName":"Program","condition":"PROG_COM_ID like 'CM%' AND OWNER_FLG='CM'","upSw":"T","frSw":"T","inSw":"T","table":"CI_MD_PRG_COM","dlSw":"F"},{"exclution":"VERSION","objName":"Program","condition":"UPPER(LOC_ID) like 'CM%'  AND OWNER_FLG='CM'","upSw":"T","frSw":"T","inSw":"T","table":"CI_MD_PRG_LOC","dlSw":"F"},{"exclution":"VERSION","objName":"Program","condition":"SVC_NAME like 'CM%'  AND OWNER_FLG='CM'","upSw":"T","frSw":"T","inSw":"T","table":"CI_MD_SVC","dlSw":"F"},{"exclution":"VERSION","objName":"Program","condition":"SVC_NAME like 'CM%'  AND OWNER_FLG='CM'","upSw":"T","frSw":"T","inSw":"T","table":"CI_MD_SVC_L","dlSw":"F"},{"exclution":"VERSION","objName":"Program","condition":"((SVC_NAME like 'CM%') OR (PROG_COM_ID LIKE 'CM%')) AND OWNER_FLG='CM'","upSw":"T","frSw":"T","inSw":"T","table":"CI_MD_SVC_PRG","dlSw":"F"},{"exclution":"VERSION","objName":"Program","condition":"UPPER(NAVIGATION_KEY) like 'CM%' AND OWNER_FLG='CM'","upSw":"T","frSw":"T","inSw":"T","table":"CI_MD_NAV","dlSw":"F"},{"exclution":"VERSION","objName":"Program","condition":"PROG_COM_ID like 'CM%' AND OWNER_FLG='CM'","upSw":"T","frSw":"T","inSw":"T","table":"CI_MD_PRG_MOD","dlSw":"F"},{"exclution":"VERSION","objName":"Program","condition":"PROG_COM_ID like 'CM%' AND OWNER_FLG='CM'","upSw":"T","frSw":"T","inSw":"T","table":"CI_MD_PRG_EL_AT","dlSw":"F"},{"exclution":"VERSION","objName":"Program","condition":"PROG_COM_ID like 'CM%' AND OWNER_FLG='CM'","upSw":"T","frSw":"T","inSw":"T","table":"CI_MD_PRG_ELEM","dlSw":"F"},{"exclution":"VERSION","objName":"Program","condition":"PROG_COM_ID like 'CM%' AND OWNER_FLG='CM'","upSw":"T","frSw":"T","inSw":"T","table":"CI_MD_PRG_SEC","dlSw":"F"},{"exclution":"VERSION","objName":"Program","condition":"PROG_COM_ID like 'CM%' AND OWNER_FLG='CM'","upSw":"T","frSw":"T","inSw":"T","table":"CI_MD_PRG_SQL","dlSw":"F"},{"exclution":"VERSION","objName":"Program","condition":"UPPER(PROG_COM_ID) like 'CM%' AND OWNER_FLG='CM'","upSw":"T","frSw":"T","inSw":"T","table":"CI_MD_PRG_TAB","dlSw":"F"},{"exclution":"VERSION","objName":"Program","condition":"PROG_COM_ID like 'CM%' AND OWNER_FLG='CM'","upSw":"T","frSw":"T","inSw":"T","table":"CI_MD_PRG_VAR","dlSw":"F"}],"Currency":[{"exclution":"VERSION","objName":"Currency","condition":"","upSw":"T","frSw":"T","inSw":"T","table":"CI_CURRENCY_CD","dlSw":"F"},{"exclution":"VERSION","objName":"Currency","condition":"","upSw":"T","frSw":"T","inSw":"T","table":"CI_CURRENCY_CD_L","dlSw":"F"}],"Algorithm":[{"exclution":"VERSION","objName":"Algorithm","condition":"UPPER(ALG_CD) LIKE 'CM%' AND OWNER_FLG='CM'","upSw":"T","frSw":"T","inSw":"T","table":"CI_ALG","dlSw":"F"},{"exclution":"VERSION","objName":"Algorithm","condition":"UPPER(ALG_CD) LIKE 'CM%' AND OWNER_FLG='CM'","upSw":"T","frSw":"T","inSw":"T","table":"CI_ALG_L","dlSw":"F"},{"exclution":"VERSION","objName":"Algorithm","condition":"UPPER(ALG_CD) LIKE 'CM%' AND OWNER_FLG='CM'","upSw":"T","frSw":"T","inSw":"T","table":"CI_ALG_PARM","dlSw":"F"},{"exclution":"VERSION","objName":"Algorithm","condition":"UPPER(ALG_CD) LIKE 'CM%' AND OWNER_FLG='CM'","upSw":"T","frSw":"T","inSw":"T","table":"CI_ALG_VER","dlSw":"F"}],"XAI Inbound Service":[{"exclution":"VERSION","objName":"XAI Inbound Service","condition":"XAI_IN_SVC_ID like 'CM%' AND OWNER_FLG='CM'","upSw":"T","frSw":"T","inSw":"T","table":"CI_XAI_IN_SVC","dlSw":"F"},{"exclution":"VERSION","objName":"XAI Inbound Service","condition":"XAI_IN_SVC_ID like 'CM%' AND OWNER_FLG='CM'","upSw":"T","frSw":"T","inSw":"T","table":"CI_XAI_IN_SVC_L","dlSw":"F"}],"Batch Control":[{"exclution":"VERSION","objName":"Batch Control","condition":"BATCH_CD like 'CM%' AND OWNER_FLG='CM'","upSw":"T","frSw":"T","inSw":"T","table":"CI_BATCH_CTRL_P","dlSw":"F"},{"exclution":"VERSION","objName":"Batch Control","condition":"BATCH_CD like 'CM%' AND OWNER_FLG='CM'","upSw":"T","frSw":"T","inSw":"T","table":"CI_BATCH_CTRL_P_L","dlSw":"F"},{"exclution":"VERSION,LAST_UPDATE_DTTM,NEXT_BATCH_NBR,LAST_UPDATE_INST","objName":"Batch Control","condition":"BATCH_CD like 'CM%' AND OWNER_FLG='CM'","upSw":"T","frSw":"T","inSw":"T","table":"CI_BATCH_CTRL","dlSw":"F"},{"exclution":"VERSION","objName":"Batch Control","condition":"BATCH_CD like 'CM%' AND OWNER_FLG='CM'","upSw":"T","frSw":"T","inSw":"T","table":"CI_BATCH_CTRL_L","dlSw":"F"}],"XAI Class":[{"exclution":"VERSION","objName":"XAI Class","condition":"OWNER_FLG='CM'","upSw":"T","frSw":"T","inSw":"T","table":"CI_XAI_CLASS","dlSw":"F"},{"exclution":"VERSION","objName":"XAI Class","condition":"OWNER_FLG='CM'","upSw":"T","frSw":"T","inSw":"T","table":"CI_XAI_CLASS_L","dlSw":"F"}],"Messages":[{"exclution":"VERSION","objName":"Messages","condition":"MESSAGE_CAT_NBR between 90000 and 99999 AND OWNER_FLG='CM'","upSw":"T","frSw":"T","inSw":"T","table":"CI_MSG_CATEGORY","dlSw":"F"},{"exclution":"VERSION","objName":"Messages","condition":"MESSAGE_CAT_NBR between 90000 and 99999 AND OWNER_FLG='CM'","upSw":"T","frSw":"T","inSw":"T","table":"CI_MSG_CATEGORY_L","dlSw":"F"},{"exclution":"VERSION","objName":"Messages","condition":"MESSAGE_CAT_NBR between 90000 and 99999 AND OWNER_FLG='CM'","upSw":"T","frSw":"T","inSw":"T","table":"CI_MSG","dlSw":"F"},{"exclution":"DESCRLONG_OVRD,VERSION","objName":"Messages","condition":"MESSAGE_CAT_NBR between 90000 and 99999 and (DESCRLONG_OVRD IS NOT NULL OR DESCRLONG_OVRD != ' ') AND OWNER_FLG='CM'","upSw":"T","frSw":"T","inSw":"T","table":"CI_MSG_L","dlSw":"F"}],"Business Objects":[{"exclution":"VERSION","objName":"Business Objects","condition":"UPPER(BUS_OBJ_CD) LIKE 'CM%' AND OWNER_FLG='CM'","upSw":"T","frSw":"T","inSw":"T","table":"F1_BUS_OBJ","dlSw":"F"},{"exclution":"VERSION","objName":"Business Objects","condition":"UPPER(BUS_OBJ_CD) LIKE 'CM%' AND UPPER(BO_SEVT_FLG) LIKE 'CM%' AND UPPER(ALG_CD) LIKE 'CM%' AND OWNER_FLG='CM'","upSw":"T","frSw":"T","inSw":"T","table":"F1_BUS_OBJ_ALG","dlSw":"F"},{"exclution":"VERSION","objName":"Business Objects","condition":"UPPER(BUS_OBJ_CD) LIKE 'CM%' AND OWNER_FLG='CM'","upSw":"T","frSw":"T","inSw":"T","table":"F1_BUS_OBJ_L","dlSw":"F"},{"exclution":"VERSION","objName":"Business Objects","condition":"UPPER(BUS_OBJ_CD) LIKE 'CM%' AND UPPER(BUS_OBJ_OPT_FLG) LIKE 'CM%' AND UPPER(BUS_OBJ_OPT_VAL) LIKE 'CM%' AND OWNER_FLG='CM'","upSw":"T","frSw":"T","inSw":"T","table":"F1_BUS_OBJ_OPT","dlSw":"F"},{"exclution":"VERSION","objName":"Business Objects","condition":"UPPER(BUS_OBJ_CD) LIKE 'CM%' AND UPPER(BO_STATUS_CD) LIKE 'CM%' AND OWNER_FLG='CM'","upSw":"T","frSw":"T","inSw":"T","table":"F1_BUS_OBJ_STATUS","dlSw":"F"},{"exclution":"VERSION","objName":"Business Objects","condition":"UPPER(BUS_OBJ_CD) LIKE 'CM%' AND UPPER(BO_STATUS_CD) LIKE 'CM%' AND UPPER(BO_STATUS_SEVT_FLG) LIKE 'CM%' AND UPPER(ALG_CD) LIKE 'CM%' AND OWNER_FLG='CM'","upSw":"T","frSw":"T","inSw":"T","table":"F1_BUS_OBJ_STATUS_ALG","dlSw":"F"},{"exclution":"VERSION","objName":"Business Objects","condition":"UPPER(BUS_OBJ_CD) LIKE 'CM%'  AND UPPER(BO_STATUS_CD) LIKE 'CM%' AND OWNER_FLG='CM'","upSw":"T","frSw":"T","inSw":"T","table":"F1_BUS_OBJ_STATUS_L","dlSw":"F"},{"exclution":"VERSION","objName":"Business Objects","condition":"UPPER(BUS_OBJ_CD) LIKE 'CM%' AND UPPER(BO_STATUS_CD) LIKE 'CM%' AND UPPER(BO_OPT_FLG) LIKE 'CM%' AND OWNER_FLG='CM'","upSw":"T","frSw":"T","inSw":"T","table":"F1_BUS_OBJ_STATUS_OPT","dlSw":"F"},{"exclution":"VERSION","objName":"Business Objects","condition":"UPPER(BUS_OBJ_CD) LIKE 'CM%' AND UPPER(BO_STATUS_CD) LIKE 'CM%' AND UPPER(BO_NEXT_STATUS_CD) LIKE 'CM%' AND OWNER_FLG='CM'","upSw":"T","frSw":"T","inSw":"T","table":"F1_BUS_OBJ_TR_RULE","dlSw":"F"},{"exclution":"VERSION","objName":"Business Objects","condition":"UPPER(BUS_OBJ_CD) LIKE 'CM%' AND UPPER(BO_STATUS_CD) LIKE 'CM%' AND UPPER(BO_NEXT_STATUS_CD) LIKE 'CM%' AND OWNER_FLG='CM'","upSw":"T","frSw":"T","inSw":"T","table":"F1_BUS_OBJ_TR_RULE_L","dlSw":"F"}],"Business Services":[{"exclution":"VERSION","objName":"Business Services","condition":"UPPER(BUS_SVC_CD) LIKE 'CM%' AND OWNER_FLG='CM'","upSw":"T","frSw":"T","inSw":"T","table":"F1_BUS_SVC","dlSw":"F"},{"exclution":"VERSION","objName":"Business Services","condition":"UPPER(BUS_SVC_CD) LIKE 'CM%' AND OWNER_FLG='CM'","upSw":"T","frSw":"T","inSw":"T","table":"F1_BUS_SVC_L","dlSw":"F"}],"MD_WRK*":[{"exclution":"VERSION","objName":"MD_WRK*","condition":"WRK_TBL_NAME like 'CM%' AND OWNER_FLG='CM'","upSw":"T","frSw":"T","inSw":"T","table":"CI_MD_WRK_TBL","dlSw":"F"},{"exclution":"VERSION","objName":"MD_WRK*","condition":"WRK_TBL_NAME like 'CM%' AND OWNER_FLG='CM'","upSw":"T","frSw":"T","inSw":"T","table":"CI_MD_WRK_TBLFLD","dlSw":"F"},{"exclution":"VERSION","objName":"MD_WRK*","condition":"WRK_TBL_NAME like 'CM%' AND OWNER_FLG='CM'","upSw":"T","frSw":"T","inSw":"T","table":"CI_MD_WRK_TBL_L","dlSw":"F"}],"Maintenance Object Algorithms":[{"exclution":"VERSION","objName":"Maintenance Object Algorithms","condition":"UPPER(MAINT_OBJ_CD) LIKE 'CM%' AND UPPER(MAINT_OBJ_SEVT_FLG) LIKE 'CM%'  AND UPPER(ALG_CD) LIKE 'CM%' AND OWNER_FLG='CM'","upSw":"T","frSw":"T","inSw":"T","table":"CI_MD_MO_ALG","dlSw":"F"}],"XAI Adapter":[{"exclution":"VERSION","objName":"XAI Adapter","condition":"OWNER_FLG='CM'","upSw":"T","frSw":"T","inSw":"T","table":"CI_XAI_ADAPTER","dlSw":"F"},{"exclution":"VERSION","objName":"XAI Adapter","condition":"OWNER_FLG='CM'","upSw":"T","frSw":"T","inSw":"T","table":"CI_XAI_ADAPTER_L","dlSw":"F"}],"Menu*":[{"exclution":"VERSION","objName":"Menu*","condition":"MENU_NAME like 'CM%' AND OWNER_FLG='CM'","upSw":"T","frSw":"T","inSw":"T","table":"CI_MD_MENU","dlSw":"F"},{"exclution":"VERSION","objName":"Menu*","condition":"MENU_NAME like 'CM%' AND OWNER_FLG='CM'","upSw":"T","frSw":"T","inSw":"T","table":"CI_MD_MENU_L","dlSw":"F"},{"exclution":"VERSION","objName":"Menu*","condition":"MENU_ITEM_ID like 'CM%' AND OWNER_FLG='CM'","upSw":"T","frSw":"T","inSw":"T","table":"CI_MD_MENU_ITEM","dlSw":"F"},{"exclution":"VERSION","objName":"Menu*","condition":"MENU_ITEM_ID like 'CM%' AND OWNER_FLG='CM'","upSw":"T","frSw":"T","inSw":"T","table":"CI_MD_MENU_ITEM_L","dlSw":"F"},{"exclution":"VERSION","objName":"Menu*","condition":"MENU_LINE_ID like 'CM%' AND OWNER_FLG='CM'","upSw":"T","frSw":"T","inSw":"T","table":"CI_MD_MENU_LINE","dlSw":"F"},{"exclution":"VERSION","objName":"Menu*","condition":"MENU_LINE_ID like 'CM%' AND OWNER_FLG='CM'","upSw":"T","frSw":"T","inSw":"T","table":"CI_MD_MENU_LINE_L","dlSw":"F"},{"exclution":"VERSION","objName":"Menu*","condition":"OWNER_FLG='CM'","upSw":"T","frSw":"T","inSw":"T","table":"CI_MD_MENU_IMOD","dlSw":"F"},{"exclution":"VERSION","objName":"Menu*","condition":"OWNER_FLG='CM'","upSw":"T","frSw":"T","inSw":"T","table":"CI_MD_MENU_MOD","dlSw":"F"}],"Table":[{"exclution":"VERSION,AUDIT_TBL_NAME,AUDIT_PGM_NAME","objName":"Table","condition":"TBL_NAME like 'CM%' AND OWNER_FLG='CM'","upSw":"T","frSw":"T","inSw":"T","table":"CI_MD_TBL","dlSw":"F"},{"exclution":"VERSION","objName":"Table","condition":"TBL_NAME like 'CM%' AND OWNER_FLG='CM'","upSw":"T","frSw":"T","inSw":"T","table":"CI_MD_TBL_L","dlSw":"F"}],"XAI Env Handler*":[{"exclution":"VERSION","objName":"XAI Env Handler*","condition":"XAI_ENV_HNDL_ID LIKE 'CM%' AND OWNER_FLG='CM'","upSw":"T","frSw":"T","inSw":"T","table":"CI_XAI_ENV_HNDL","dlSw":"F"},{"exclution":"VERSION","objName":"XAI Env Handler*","condition":"XAI_ENV_HNDL_ID LIKE 'CM%' AND OWNER_FLG='CM'","upSw":"T","frSw":"T","inSw":"T","table":"CI_XAI_ENV_HNDL_L","dlSw":"F"}],"Lookup Value":[{"exclution":"VERSION","objName":"Lookup Value","condition":"FIELD_NAME LIKE 'CM%' AND OWNER_FLG='CM'","upSw":"T","frSw":"T","inSw":"T","table":"CI_LOOKUP_VAL","dlSw":"F"},{"exclution":"VERSION","objName":"Lookup Value","condition":"FIELD_NAME LIKE 'CM%' AND OWNER_FLG='CM'","upSw":"T","frSw":"T","inSw":"T","table":"CI_LOOKUP_VAL_L","dlSw":"F"}],"Application Service":[{"exclution":"VERSION","objName":"Application Service","condition":"APP_SVC_ID like 'CM%'  AND OWNER_FLG='CM'","upSw":"T","frSw":"T","inSw":"T","table":"SC_APP_SERVICE","dlSw":"F"},{"exclution":"VERSION","objName":"Application Service","condition":"APP_SVC_ID like 'CM%' AND OWNER_FLG='CM'","upSw":"T","frSw":"T","inSw":"T","table":"SC_APP_SERVICE_L","dlSw":"F"}],"User Navigation Link*":[{"exclution":"VERSION","objName":"User Navigation Link*","condition":"USER_ID IN ('CDX') AND UPPER(NAV_OPT_CD) like 'CM%'","upSw":"T","frSw":"T","inSw":"T","table":"CI_USR_NAV_LINK","dlSw":"F"}],"MD_SO*":[{"exclution":"VERSION","objName":"MD_SO*","condition":"SO_CD like 'CM%' AND OWNER_FLG='CM'","upSw":"T","frSw":"T","inSw":"T","table":"CI_MD_SO","dlSw":"F"},{"exclution":"VERSION","objName":"MD_SO*","condition":"SO_CD like 'CM%' AND OWNER_FLG='CM'","upSw":"T","frSw":"T","inSw":"T","table":"CI_MD_SOCG","dlSw":"F"},{"exclution":"VERSION","objName":"MD_SO*","condition":"SO_CD like 'CM%' AND OWNER_FLG='CM'","upSw":"T","frSw":"T","inSw":"T","table":"CI_MD_SOCG_FLD","dlSw":"F"},{"exclution":"VERSION","objName":"MD_SO*","condition":"SO_CD like 'CM%' AND OWNER_FLG='CM'","upSw":"T","frSw":"T","inSw":"T","table":"CI_MD_SOCG_FLDAT","dlSw":"F"},{"exclution":"VERSION","objName":"MD_SO*","condition":"SO_CD like 'CM%' AND OWNER_FLG='CM'","upSw":"T","frSw":"T","inSw":"T","table":"CI_MD_SOCG_L","dlSw":"F"},{"exclution":"VERSION","objName":"MD_SO*","condition":"SO_CD like 'CM%' AND OWNER_FLG='CM'","upSw":"T","frSw":"T","inSw":"T","table":"CI_MD_SOCG_SORT","dlSw":"F"},{"exclution":"VERSION","objName":"MD_SO*","condition":"SO_CD like 'CM%' AND OWNER_FLG='CM'","upSw":"T","frSw":"T","inSw":"T","table":"CI_MD_SO_L","dlSw":"F"},{"exclution":"VERSION","objName":"MD_SO*","condition":"SO_CD like 'CM%' AND OWNER_FLG='CM'","upSw":"T","frSw":"T","inSw":"T","table":"CI_MD_SO_RSFLD","dlSw":"F"},{"exclution":"VERSION","objName":"MD_SO*","condition":"SO_CD like 'CM%' AND OWNER_FLG='CM'","upSw":"T","frSw":"T","inSw":"T","table":"CI_MD_SO_RSFLDAT","dlSw":"F"}],"XAI Executor":[{"exclution":"VERSION","objName":"XAI Executor","condition":"OWNER_FLG='CM'","upSw":"T","frSw":"T","inSw":"T","table":"CI_XAI_EXECUTER","dlSw":"F"},{"exclution":"VERSION","objName":"XAI Executor","condition":"OWNER_FLG='CM'","upSw":"T","frSw":"T","inSw":"T","table":"CI_XAI_EXECUTER_L","dlSw":"F"}],"Algorithm Type":[{"exclution":"VERSION","objName":"Algorithm Type","condition":"ALG_TYPE_CD like 'CM%' AND OWNER_FLG='CM'","upSw":"T","frSw":"T","inSw":"T","table":"CI_ALG_TYPE","dlSw":"F"},{"exclution":"VERSION","objName":"Algorithm Type","condition":"ALG_TYPE_CD like 'CM%' AND OWNER_FLG='CM'","upSw":"T","frSw":"T","inSw":"T","table":"CI_ALG_TYPE_L","dlSw":"F"},{"exclution":"VERSION","objName":"Algorithm Type","condition":"ALG_TYPE_CD like 'CM%' AND OWNER_FLG='CM'","upSw":"T","frSw":"T","inSw":"T","table":"CI_ALG_TYPE_PRM","dlSw":"F"},{"exclution":"VERSION","objName":"Algorithm Type","condition":"ALG_TYPE_CD like 'CM%' AND OWNER_FLG='CM'","upSw":"T","frSw":"T","inSw":"T","table":"CI_ALG_TYPE_PRM_L","dlSw":"F"}],"Table Field":[{"exclution":"VERSION,AUDIT_INSERT_SW,AUDIT_UPDATE_SW,AUDIT_DELETE_SW","objName":"Table Field","condition":"TBL_NAME like 'CM%' AND OWNER_FLG='CM'","upSw":"T","frSw":"T","inSw":"T","table":"CI_MD_TBL_FLD","dlSw":"F"},{"exclution":"VERSION","objName":"Table Field","condition":"TBL_NAME like 'CM%' AND OWNER_FLG='CM'","upSw":"T","frSw":"T","inSw":"T","table":"CI_MD_TBL_FLD_L","dlSw":"F"}],"DB INSTR*":[{"exclution":"VERSION","objName":"DB INSTR*","condition":"DB_PROC_CD like 'CM%' AND OWNER_FLG='CM'","upSw":"T","frSw":"T","inSw":"T","table":"CI_DB_INSTR","dlSw":"F"},{"exclution":"VERSION","objName":"DB INSTR*","condition":"DB_PROC_CD like 'CM%'","upSw":"T","frSw":"T","inSw":"T","table":"CI_DB_INSTR_L","dlSw":"F"},{"exclution":"VERSION","objName":"DB INSTR*","condition":"DB_PROC_CD like 'CM%'","upSw":"T","frSw":"T","inSw":"T","table":"CI_DB_INST_OVRD","dlSw":"F"}],"Maintenance Object":[{"exclution":"VERSION","objName":"Maintenance Object","condition":"MAINT_OBJ_CD like 'CM%' AND OWNER_FLG='CM'","upSw":"T","frSw":"T","inSw":"T","table":"CI_MD_MO","dlSw":"F"},{"exclution":"VERSION","objName":"Maintenance Object","condition":"MAINT_OBJ_CD like 'CM%' AND OWNER_FLG='CM'","upSw":"T","frSw":"T","inSw":"T","table":"CI_MD_MO_L","dlSw":"F"},{"exclution":"VERSION","objName":"Maintenance Object","condition":"MAINT_OBJ_CD like 'CM%' AND OWNER_FLG='CM'","upSw":"T","frSw":"T","inSw":"T","table":"CI_MD_MO_TBL","dlSw":"F"},{"exclution":"VERSION","objName":"Maintenance Object","condition":"MAINT_OBJ_CD like 'CM%' AND OWNER_FLG='CM'","upSw":"T","frSw":"T","inSw":"T","table":"CI_MD_MO_WRK","dlSw":"F"}],"User Group":[{"exclution":"VERSION","objName":"User Group","condition":"(USR_GRP_ID = 'ALL_SERVICES' and APP_SVC_ID like 'CM%' AND OWNER_FLG='CM')","upSw":"T","frSw":"T","inSw":"T","table":"SC_USR_GRP_PROF","dlSw":"F"},{"exclution":"VERSION","objName":"User Group","condition":"(USR_GRP_ID = 'ALL_SERVICES' and APP_SVC_ID like 'CM%' AND OWNER_FLG='CM')","upSw":"T","frSw":"T","inSw":"T","table":"SC_ACCESS_CNTL","dlSw":"F"},{"exclution":"VERSION","objName":"User Group","condition":"APP_SVC_ID like 'CM%' AND OWNER_FLG='CM'","upSw":"T","frSw":"T","inSw":"T","table":"CI_APP_SVC_ACC","dlSw":"F"}],"Schema":[{"exclution":"VERSION","objName":"Schema","condition":"UPPER(SCHEMA_NAME) LIKE 'CM%' AND UPPER(SCHEMA_TYPE_FLG) LIKE 'CM%' AND OWNER_FLG='CM'","upSw":"T","frSw":"T","inSw":"T","table":"F1_SCHEMA","dlSw":"F"}],"Tab Mod":[{"exclution":"VERSION","objName":"Tab Mod","condition":"OWNER_FLG='CM'","upSw":"T","frSw":"T","inSw":"T","table":"CI_MD_TAB_MOD","dlSw":"F"}],"Characteristic Entities":[{"exclution":"VERSION","objName":"Characteristic Entities","condition":"UPPER(CHAR_ENTITY_FLG) LIKE 'CM%' AND UPPER(CHAR_TYPE_CD) LIKE 'CM%' AND OWNER_FLG='CM'","upSw":"T","frSw":"T","inSw":"T","table":"CI_CHAR_ENTITY","dlSw":"F"},{"exclution":"VERSION","objName":"Characteristic Entities","condition":"UPPER(CHAR_TYPE_CD) LIKE 'CM%' AND OWNER_FLG='CM'","upSw":"T","frSw":"T","inSw":"T","table":"CI_CHAR_TYPE","dlSw":"F"},{"exclution":"VERSION","objName":"Characteristic Entities","condition":"UPPER(CHAR_TYPE_CD) LIKE 'CM%' AND OWNER_FLG='CM'","upSw":"T","frSw":"T","inSw":"T","table":"CI_CHAR_TYPE_L","dlSw":"F"},{"exclution":"VERSION","objName":"Characteristic Entities","condition":"UPPER(CHAR_TYPE_CD) LIKE 'CM%' AND UPPER(CHAR_VAL) LIKE 'CM%' AND OWNER_FLG='CM'","upSw":"T","frSw":"T","inSw":"T","table":"CI_CHAR_VAL","dlSw":"F"},{"exclution":"VERSION","objName":"Characteristic Entities","condition":"UPPER(CHAR_TYPE_CD) LIKE 'CM%' AND UPPER(CHAR_VAL) LIKE 'CM%' AND OWNER_FLG='CM'","upSw":"T","frSw":"T","inSw":"T","table":"CI_CHAR_VAL_L","dlSw":"F"}],"Display Icon*":[{"exclution":"VERSION","objName":"Display Icon*","condition":"DISP_ICON_CD like 'CM%' AND OWNER_FLG='CM'","upSw":"T","frSw":"T","inSw":"T","table":"CI_DISP_ICON","dlSw":"F"},{"exclution":"VERSION","objName":"Display Icon*","condition":"DISP_ICON_CD like 'CM%' AND OWNER_FLG='CM'","upSw":"T","frSw":"T","inSw":"T","table":"CI_DISP_ICON_L","dlSw":"F"}],"CM Packaging":[],"Data Area":[{"exclution":"VERSION","objName":"Data Area","condition":"UPPER(DATA_AREA_CD) LIKE 'CM%' AND OWNER_FLG='CM'","upSw":"T","frSw":"T","inSw":"T","table":"F1_DATA_AREA","dlSw":"F"},{"exclution":"VERSION","objName":"Data Area","condition":"UPPER(DATA_AREA_CD) LIKE 'CM%' AND OWNER_FLG='CM'","upSw":"T","frSw":"T","inSw":"T","table":"F1_DATA_AREA_L","dlSw":"F"}],"Lookup":[{"exclution":"VERSION","objName":"Lookup","condition":"FIELD_NAME like 'CM%'  AND OWNER_FLG='CM'","upSw":"T","frSw":"T","inSw":"T","table":"CI_LOOKUP_FIELD","dlSw":"F"}],"XAI Format*":[{"exclution":"VERSION","objName":"XAI Format*","condition":"","upSw":"T","frSw":"T","inSw":"T","table":"CI_XAI_FORMAT","dlSw":"F"},{"exclution":"VERSION","objName":"XAI Format*","condition":"","upSw":"T","frSw":"T","inSw":"T","table":"CI_XAI_FORMAT_L","dlSw":"F"}],"TRG*":[{"exclution":"VERSION","objName":"TRG*","condition":"OWNER_FLG='CM'","upSw":"T","frSw":"T","inSw":"T","table":"CI_TRG","dlSw":"F"},{"exclution":"VERSION","objName":"TRG*","condition":"OWNER_FLG='CM'","upSw":"T","frSw":"T","inSw":"T","table":"CI_TRG_FLD","dlSw":"F"}],"PDF*":[{"exclution":"VERSION","objName":"PDF*","condition":"OWNER_FLG='CM'","upSw":"T","frSw":"T","inSw":"T","table":"CI_MD_PDF","dlSw":"F"},{"exclution":"VERSION","objName":"PDF*","condition":"OWNER_FLG='CM'","upSw":"T","frSw":"T","inSw":"T","table":"CI_MD_PDF_VAL","dlSw":"F"}]}